pre_processing.cp36-win32.pyd
pre_processing/.libs/libmask_int.AB76W5GMFL5QMAFF642LCBGZAMXKXIZ3.gfortran-win32.dll
mask_generation-0.0.1.dist-info/LICENSE
mask_generation-0.0.1.dist-info/METADATA
mask_generation-0.0.1.dist-info/WHEEL
mask_generation-0.0.1.dist-info/top_level.txt
mask_generation-0.0.1.dist-info/RECORD
