Metadata-Version: 2.1
Name: mask-generation
Version: 0.0.1
Summary: build mask files for wyvern code
Home-page: https://github.com/ly16302/mask
Author: Liang Yang
Author-email: liang.yang@cranfield.ac.uk
License: Apache-2.0
Keywords: f2py
Platform: UNKNOWN
License-File: LICENSE
